aio_mqtt/__init__.py
aio_mqtt/client.py
aio_mqtt/constants.py
aio_mqtt/enums.py
aio_mqtt/exceptions.py
aio_mqtt/utils.py
aio_mqtt/version.py
aio_mqtt_mod-0.4.0.dist-info/licenses/LICENSE
aio_mqtt_mod-0.4.0.dist-info/METADATA
aio_mqtt_mod-0.4.0.dist-info/WHEEL
aio_mqtt_mod-0.4.0.dist-info/top_level.txt
aio_mqtt_mod-0.4.0.dist-info/RECORD
