Metadata-Version: 2.4
Name: aio-mqtt-mod
Version: 0.4.0
Summary: Asynchronous MQTT client for 3.1.1 protocol version.
Home-page: https://github.com/devbis/aio-mqtt
Author: Not Just A Toy Corp.
Author-email: dev@notjustatoy.com
License: Apache License 2.0
Keywords: mqtt asyncio
Classifier: Development Status :: 4 - Beta
Classifier: Intended Audience :: Developers
Classifier: License :: OSI Approved :: Apache Software License
Classifier: Operating System :: MacOS :: MacOS X
Classifier: Operating System :: Microsoft :: Windows
Classifier: Operating System :: POSIX
Classifier: Natural Language :: English
Classifier: Programming Language :: Python
Classifier: Programming Language :: Python :: 3
Classifier: Topic :: Communications
Classifier: Topic :: Internet
Requires-Python: >=3.9.0
License-File: LICENSE
Dynamic: author
Dynamic: author-email
Dynamic: classifier
Dynamic: description
Dynamic: home-page
Dynamic: keywords
Dynamic: license
Dynamic: license-file
Dynamic: requires-python
Dynamic: summary
